upgradechat/__init__.py
upgradechat/models.py
upgradechatpy-1.0.5.dist-info/LICENSE
upgradechatpy-1.0.5.dist-info/METADATA
upgradechatpy-1.0.5.dist-info/WHEEL
upgradechatpy-1.0.5.dist-info/top_level.txt
upgradechatpy-1.0.5.dist-info/RECORD
