Metadata-Version: 2.1
Name: upgradechatpy
Version: 1.0.5
Summary: A wrapper around Upgrade.Chat's API
Home-page: https://github.com/Voxel-Fox-Ltd/UpgradeChat
Author: Kae Bartlett
Author-email: kae@voxelfox.co.uk
License: UNKNOWN
Platform: UNKNOWN
Classifier: Programming Language :: Python :: 3
Classifier: License :: OSI Approved :: GNU General Public License v2 (GPLv2)
Classifier: Operating System :: OS Independent
Requires-Python: >=3.6
Provides-Extra: docs
